quicktests/__init__.py
test/__init__.py
quicktests-0.0.4.dist-info/LICENSE
quicktests-0.0.4.dist-info/METADATA
quicktests-0.0.4.dist-info/WHEEL
quicktests-0.0.4.dist-info/top_level.txt
quicktests-0.0.4.dist-info/RECORD
