Metadata-Version: 2.1
Name: quicktests
Version: 0.0.4
Summary: A library for python for easy testing.
Home-page: https://gitlab.com/Raspilot/quicktests
Author: Fabian Becker
Author-email: fab.becker@outlook.de
License: UNKNOWN
Platform: UNKNOWN
Classifier: Programming Language :: Python :: 3
Classifier: License :: OSI Approved :: GNU General Public License v3 (GPLv3)
Classifier: Operating System :: OS Independent
Requires-Python: >=3.6
